<?xml version="1.0" encoding="ISO-8859-15" ?>
<rdf:RDF
  xmlns:rdf="http://www.w3.org/1999/02/22-rdf-syntax-ns#"
  xmlns:dc="http://purl.org/dc/elements/1.1/"
  xmlns:sy="http://purl.org/rss/1.0/modules/syndication/"
  xmlns:admin="http://webns.net/mvcb/"
  xmlns:content="http://purl.org/rss/1.0/modules/content/"
  xmlns="http://purl.org/rss/1.0/">

<channel rdf:about="https://kidpaddleetcieglin.skyrock.com/">
  <title> c&#039;est super la WII (flipnote) - Commentaires</title>
  <description>Luigi vient de finir une Triforce avec des cartes (clin d&#039;oeil pour fêter les 25 ans de the legend of Zelda) qu&#039;il a mis plus d&#039;un an à faire. Soudain Mario débarqua et dégomma sa Triforce de cartes. A ce moment là, Luigi qui voulait prendre sa Triforce en photo, pour l&#039;immortaliser, n&#039;avait plus que la la grosse tète de Mario dans l&#039;objectif. Mario le consola alors en lui disant qu&#039;il avait acheté la WII. Luigi voulu alors la tester, pensant que le maniement serait difficile. Il demanda alors à Mario des explicationS, Mario lui montra alors l&#039;ingéniosité et toutes les possibilités de gameplay qu&#039;offrait la WII, mais il s&#039;avérait que c&#039;était pas grand chose vu qu&#039;il suffit de secouer la Wiimote. Mario fit alors la réflexion &quot;Bizarrement Peach adore la WII&quot; 




</description>
  <link>https://kidpaddleetcieglin.skyrock.com/</link>
  <dc:language>fr</dc:language>
  <dc:creator>KidpaddleetcieGlin</dc:creator>
  <dc:rights></dc:rights>
  <dc:date>2023-06-15T01:03:13+02:00</dc:date>
  <admin:generatorAgent rdf:resource="https://www.skyrock.com/" />

  <sy:updatePeriod>daily</sy:updatePeriod>
  <sy:updateFrequency>1</sy:updateFrequency>
  <sy:updateBase>2023-06-15T01:03:13+02:00</sy:updateBase>

  <items>
  <rdf:Seq>
      </rdf:Seq>
  </items>
</channel>
    </rdf:RDF>