<?xml version="1.0" encoding="ISO-8859-15" ?>
<rdf:RDF
  xmlns:rdf="http://www.w3.org/1999/02/22-rdf-syntax-ns#"
  xmlns:dc="http://purl.org/dc/elements/1.1/"
  xmlns:sy="http://purl.org/rss/1.0/modules/syndication/"
  xmlns:admin="http://webns.net/mvcb/"
  xmlns:content="http://purl.org/rss/1.0/modules/content/"
  xmlns="http://purl.org/rss/1.0/">

<channel rdf:about="https://kidpaddleetcieglin.skyrock.com/">
  <title> [Événement]Kidpaddleetcie Glin a 18 ans! - Commentaires</title>
  <description>Salutation jeune/vieux internaute!
Ce samedi 5 juillet 2014,j&#039;ai eût 18 ans (l&#8217;âge de la majorité)!
 
Bon,vous vous doutez bien que ça fait un paquet de chose en plus dans ma vie en terme de droit mais je pense rester encore longtemps avec les parents et ma petite s½ur FanYoshiBleu ^^
 
Pour le moment,ce changement n&#039;affecte en rien mon contenu sur internet mais c&#039;est quand même la possibilité de pouvoir m&#039;absenter un moment pour aller chercher l&#039;inspiration sans avoir les parents sous le contrôle total :)
 
Allez,à bientôt les petits lardons (références à Bla-Bla)!</description>
  <link>https://kidpaddleetcieglin.skyrock.com/</link>
  <dc:language>fr</dc:language>
  <dc:creator>KidpaddleetcieGlin</dc:creator>
  <dc:rights></dc:rights>
  <dc:date>2023-06-15T01:03:13+02:00</dc:date>
  <admin:generatorAgent rdf:resource="https://www.skyrock.com/" />

  <sy:updatePeriod>daily</sy:updatePeriod>
  <sy:updateFrequency>1</sy:updateFrequency>
  <sy:updateBase>2023-06-15T01:03:13+02:00</sy:updateBase>

  <items>
  <rdf:Seq>
      </rdf:Seq>
  </items>
</channel>
    </rdf:RDF>